agent/__main__.py
agent/agent.py
agent/state_machine.py
agent/interface/__init__.py
agent/interface/cli_interface.py
agent/llm/__init__.py
agent/llm/local.py
agent/llm/tokenizer.py
agent/llm/control_tokens/__init__.py
agent/llm/control_tokens/chatml.json
agent/llm/control_tokens/hermes.json
agent/llm/control_tokens/llama.json
agent/llm/control_tokens/mistral.json
agent/llm/frontend/__init__.py
agent/llm/frontend/mlx.py
agent/llm/frontend/torch.py
agent/llm/prompts/__init__.py
agent/llm/prompts/base.txt
agent/llm/prompts/chat_template.jinja
agent/mcp/__init__.py
agent/mcp/client.py
agent/mcp/host.py
agent/mcp/server.py
agent/mcp/servers/servers_list.json
agent/state/__init__.py
agent/state/action/python.py
agent/state/action/tool_call.py
agent/state/planning/inner_monologue.py
agent/state/planning/scratchpad.py
agent/state/planning/thinking.py
agent/system/interaction.py
agent/system/memory.py
agent/system/run_python_code.py
agent/system/setup_wizard.py
agent/system/voice/__init__.py
agent/system/voice/voicebox.py
agent/tools/__init__.py
agent/tools/add_mcp_server.py
agent/tools/list_mcp_servers.py
agent/tools/send_message.py
proxy_base_agent-1.0.1.dist-info/METADATA
proxy_base_agent-1.0.1.dist-info/WHEEL
proxy_base_agent-1.0.1.dist-info/RECORD
