Metadata-Version: 2.4
Name: proxy-base-agent
Version: 1.0.1
Summary: A stateful, tool-enabled agent powered by the Proxy Structuring Engine.
Project-URL: homepage, https://github.com/TheProxyCompany/proxy-base-agent
Project-URL: documentation, https://github.com/TheProxyCompany/proxy-base-agent#readme
Project-URL: source, https://github.com/TheProxyCompany/proxy-base-agent
Author-email: Jack Wind <jckwind11@gmail.com>, The Proxy Company <contact@theproxy.company>
Requires-Python: >=3.11
Requires-Dist: docstring-parser>=0.16
Requires-Dist: huggingface-hub>=0.28.1
Requires-Dist: imgcat>=0.6.0
Requires-Dist: kokoro-onnx
Requires-Dist: mcp
Requires-Dist: numpy
Requires-Dist: pillow
Requires-Dist: pse
Requires-Dist: pydantic>=2.10.5
Requires-Dist: pygithub
Requires-Dist: pynput
Requires-Dist: python-dotenv>=1.0.1
Requires-Dist: questionary>=2.1.0
Requires-Dist: rich
Requires-Dist: ruff
Requires-Dist: sounddevice
Provides-Extra: mlx
Requires-Dist: mlx-proxy; extra == 'mlx'
Provides-Extra: torch
Requires-Dist: accelerate; extra == 'torch'
Requires-Dist: torch; extra == 'torch'
